mongomock_persistence/__init__.py
mongomock_persistence/database.py
mongomock_persistence/store.py
mongomock_persistence-0.0.5.dist-info/LICENSE
mongomock_persistence-0.0.5.dist-info/METADATA
mongomock_persistence-0.0.5.dist-info/WHEEL
mongomock_persistence-0.0.5.dist-info/top_level.txt
mongomock_persistence-0.0.5.dist-info/RECORD
